gdaps/__init__.py
gdaps/admin.py
gdaps/apps.py
gdaps/conf.py
gdaps/exceptions.py
gdaps/hooks.py
gdaps/models.py
gdaps/pluginmanager.py
gdaps/validators.py
gdaps/api/__init__.py
gdaps/api/interfaces.py
gdaps/drf/__init__.py
gdaps/drf/apps.py
gdaps/drf/urls.py
gdaps/graphene/__init__.py
gdaps/graphene/api.py
gdaps/graphene/apps.py
gdaps/graphene/schema.py
gdaps/graphene/urls.py
gdaps/management/__init__.py
gdaps/management/commands/__init__.py
gdaps/management/commands/initializeplugins.py
gdaps/management/commands/startplugin.py
gdaps/management/commands/syncplugins.py
gdaps/migrations/0001_initial.py
gdaps/migrations/0002_alter_gdapsplugin_id.py
gdaps/migrations/0003_remove_gdapsplugin_visible_gdapsplugin_hidden.py
gdaps/migrations/0004_alter_gdapsplugin_id.py
gdaps/migrations/0005_alter_gdapsplugin_id.py
gdaps/migrations/0006_alter_gdapsplugin_id.py
gdaps/migrations/0007_alter_gdapsplugin_id.py
gdaps/migrations/__init__.py
gdaps/templatetags/gdaps.py
gdaps-0.11.0.dist-info/licenses/LICENSE.md
gdaps-0.11.0.dist-info/METADATA
gdaps-0.11.0.dist-info/WHEEL
gdaps-0.11.0.dist-info/top_level.txt
gdaps-0.11.0.dist-info/RECORD
