Metadata-Version: 2.4
Name: gdaps
Version: 0.11.0
Summary: Generic plugin environment, perfectly fitting into the Django ecosystem
Author-email: Christian González <office@nerdocs.at>
License: Copyright 2019-2025 Christian González
Project-URL: Home, https://gdaps.readthedocs.org
Project-URL: Source, https://gitlab.com/nerdocs/gdaps
Project-URL: Documentation, https://gdaps.readthedocs.org
Project-URL: Tracker, https://gitlab.com/nerdocs/gdaps/issues
Keywords: django,plugins
Classifier: License :: OSI Approved :: BSD License
Classifier: Development Status :: 3 - Alpha
Classifier: Environment :: Web Environment
Classifier: Framework :: Django :: 3.2
Classifier: Intended Audience :: Developers
Classifier: Natural Language :: English
Classifier: Operating System :: OS Independent
Classifier: Programming Language :: JavaScript
Classifier: Programming Language :: Python :: 3 :: Only
Classifier: Programming Language :: Python :: 3.11
Classifier: Topic :: Internet :: WWW/HTTP
Classifier: Topic :: Internet :: WWW/HTTP :: Dynamic Content
Classifier: Topic :: Internet :: WWW/HTTP :: WSGI
Requires-Python: >=3.11
License-File: LICENSE.md
Requires-Dist: django>=5.2
Requires-Dist: nltk>=3.6
Requires-Dist: semantic-version>=2.9
Dynamic: license-file
